imax_b8_serial/__init__.py
imax_b8_serial/__main__.py
imax_b8_serial/py.typed
imax_b8_serial-0.0.1.dist-info/LICENSE
imax_b8_serial-0.0.1.dist-info/METADATA
imax_b8_serial-0.0.1.dist-info/WHEEL
imax_b8_serial-0.0.1.dist-info/entry_points.txt
imax_b8_serial-0.0.1.dist-info/top_level.txt
imax_b8_serial-0.0.1.dist-info/RECORD
