Metadata-Version: 2.1
Name: imax-b8-serial
Version: 0.0.1
Summary: Serial interface to monitor LiPo charger.
Home-page: UNKNOWN
Author: Barnaby Shearer
Author-email: b@zi.is
License: UNKNOWN
Project-URL: Source, https://github.com/BarnabyShearer/imax-b8-serial
Project-URL: Tracker, https://github.com/BarnabyShearer/imax-b8-serial/issues
Project-URL: Documentation, https://imax-b8-serial.readthedocs.io/en/latest/
Platform: UNKNOWN
Classifier: Development Status :: 5 - Production/Stable
Classifier: Programming Language :: Python :: 3
Requires-Python: >=3.7
License-File: LICENSE
Requires-Dist: pyserial
